{"restaurants": [
    {
        "contactInfo": "32423423",
        "name": "DoubleTree",
        "offerings": [
            {
                "price": 20,
                "foodType": "Thai",
                "location": "1st floor - 4400 Marriott Dr.",
                "id": 1,
                "time": "14:00-16:00"
            },
            {
                "price": 35,
                "foodType": "Barbecue",
                "location": "2nd floor - 343 Pineapple St.",
                "id": 2,
                "time": "20:00-21:00"
            }
        ]
    },
    {
        "contactInfo": "00000000",
        "name": "Walton",
        "offerings": []
    }
]}